{
  "content": [
    {
      "content": null,
      "created": "2022-03-18T17:06:57.693622Z",
      "format": null,
      "last_modified": "2022-03-18T17:05:25.596256Z",
      "mimetype": null,
      "name": "iwren.ipynb",
      "path": "xeus-wren/iwren.ipynb",
      "size": 3010,
      "type": "notebook",
      "writable": true
    }
  ],
  "created": "2022-03-18T17:06:57.693622Z",
  "format": "json",
  "last_modified": "2022-03-18T17:06:57.693622Z",
  "mimetype": null,
  "name": "xeus-wren",
  "path": "xeus-wren",
  "size": null,
  "type": "directory",
  "writable": true
}